corona/__init__.py
corona/client.py
corona/http.py
corona/objects.py
corona/router.py
corona.py-0.0.2.dist-info/LICENSE.txt
corona.py-0.0.2.dist-info/METADATA
corona.py-0.0.2.dist-info/WHEEL
corona.py-0.0.2.dist-info/top_level.txt
corona.py-0.0.2.dist-info/RECORD
