Metadata-Version: 2.1
Name: corona.py
Version: 0.0.2
Summary: An asynchronous wrapper for the corona.lmao.ninja API written in Python with Discord.py plugin.
Home-page: https://github.com/AndyTempel/corona.py
Author: NANI
Author-email: nani@ksoft.si
License: MIT
Keywords: coronavirus,covid-19,corona-statistics
Platform: UNKNOWN
Classifier: Development Status :: 4 - Beta
Classifier: License :: OSI Approved :: MIT License
Classifier: Programming Language :: Python :: 3
Classifier: Programming Language :: Python :: 3.6
Classifier: Programming Language :: Python :: 3.7
Classifier: Programming Language :: Python :: 3.8
Requires-Dist: aiohttp
